{
    "__comment": "Model generated using MrCrayfish's Model Creator (https://mrcrayfish.com/tools?id=mc)",
    "textures": {
        "0": "blocks/stone_slab_top",
        "1": "blocks/iron_block",
        "2": "em:blocks/void_singularity",
        "particle": "blocks/stone_slab_top"
    },
    "display": {
        "gui": {
            "rotation": [ 30, 225, 0 ],
            "translation": [ 0, 0, 0 ],
            "scale": [ 0.625, 0.625, 0.625 ]
        },
        "ground": {
            "rotation": [ 0, 0, 0 ],
            "translation": [ 0, 3, 0 ],
            "scale": [ 0.25, 0.25, 0.25 ]
        },
        "fixed": {
            "rotation": [ 0, 0, 0 ],
            "translation": [ 0, 0, 0 ],
            "scale": [ 0.5, 0.5, 0.5 ]
        },
        "thirdperson_righthand": {
            "rotation": [ 75, 45, 0 ],
            "translation": [ 0, 2.5, 0 ],
            "scale": [ 0.375, 0.375, 0.375 ]
        },
        "thirdperson_lefthand": {
            "rotation": [ 75, 255, 0 ],
            "translation": [ 0, 2.5, 0 ],
            "scale": [ 0.375, 0.375, 0.375 ]
        },
        "firstperson_righthand": {
            "rotation": [ 0, 45, 0 ],
            "translation": [ 0, 2.5, 0 ],
            "scale": [ 0.4, 0.4, 0.4 ]
        },
        "firstperson_lefthand": {
            "rotation": [ 0, 225, 0 ],
            "translation": [ 0, 2.5, 0 ],
            "scale": [ 0.4, 0.4, 0.4 ]
        }
    },
    "elements": [
        {
            "name": "Base",
            "from": [ 0.00, 0.00, 0.00 ], 
            "to": [ 16.00, 2.00, 16.00 ], 
            "faces": {
                "north": { "texture": "#0", "uv": [ 0.00, 0.00, 16.00, 2.00 ] },
                "east": { "texture": "#0", "uv": [ 0.00, 0.00, 16.00, 2.00 ] },
                "south": { "texture": "#0", "uv": [ 0.00, 0.00, 16.00, 2.00 ] },
                "west": { "texture": "#0", "uv": [ 0.00, 0.00, 16.00, 2.00 ] },
                "up": { "texture": "#0", "uv": [ 0.00, 0.00, 16.00, 16.00 ] },
                "down": { "texture": "#0", "uv": [ 0.00, 0.00, 16.00, 16.00 ] }
            }
        },
        {
            "name": "Stand1top3",
            "from": [ 5.00, 13.00, 12.00 ], 
            "to": [ 11.00, 14.00, 13.00 ], 
            "faces": {
                "north": { "texture": "#1", "uv": [ 0.00, 0.00, 6.00, 1.00 ] },
                "east": { "texture": "#1", "uv": [ 0.00, 0.00, 1.00, 1.00 ] },
                "south": { "texture": "#1", "uv": [ 0.00, 0.00, 6.00, 1.00 ] },
                "west": { "texture": "#1", "uv": [ 0.00, 0.00, 1.00, 1.00 ] },
                "up": { "texture": "#1", "uv": [ 0.00, 0.00, 6.00, 1.00 ] },
                "down": { "texture": "#1", "uv": [ 0.00, 0.00, 6.00, 1.00 ] }
            }
        },
        {
            "name": "Stand1top2",
            "from": [ 5.00, 14.00, 12.00 ], 
            "to": [ 6.00, 15.00, 13.00 ], 
            "faces": {
                "north": { "texture": "#1", "uv": [ 0.00, 0.00, 1.00, 1.00 ] },
                "east": { "texture": "#1", "uv": [ 0.00, 0.00, 1.00, 1.00 ] },
                "south": { "texture": "#1", "uv": [ 0.00, 0.00, 1.00, 1.00 ] },
                "west": { "texture": "#1", "uv": [ 0.00, 0.00, 1.00, 1.00 ] },
                "up": { "texture": "#1", "uv": [ 0.00, 0.00, 1.00, 1.00 ] },
                "down": { "texture": "#1", "uv": [ 0.00, 0.00, 1.00, 1.00 ] }
            }
        },
        {
            "name": "Stand1top1",
            "from": [ 10.00, 14.00, 12.00 ], 
            "to": [ 11.00, 15.00, 13.00 ], 
            "faces": {
                "north": { "texture": "#1", "uv": [ 0.00, 0.00, 1.00, 1.00 ] },
                "east": { "texture": "#1", "uv": [ 0.00, 0.00, 1.00, 1.00 ] },
                "south": { "texture": "#1", "uv": [ 0.00, 0.00, 1.00, 1.00 ] },
                "west": { "texture": "#1", "uv": [ 0.00, 0.00, 1.00, 1.00 ] },
                "up": { "texture": "#1", "uv": [ 0.00, 0.00, 1.00, 1.00 ] },
                "down": { "texture": "#1", "uv": [ 0.00, 0.00, 1.00, 1.00 ] }
            }
        },
        {
            "name": "Stand2top3",
            "from": [ 5.00, 13.00, 3.00 ], 
            "to": [ 11.00, 14.00, 4.00 ], 
            "faces": {
                "north": { "texture": "#1", "uv": [ 0.00, 0.00, 6.00, 1.00 ] },
                "east": { "texture": "#1", "uv": [ 0.00, 0.00, 1.00, 1.00 ] },
                "south": { "texture": "#1", "uv": [ 0.00, 0.00, 6.00, 1.00 ] },
                "west": { "texture": "#1", "uv": [ 0.00, 0.00, 1.00, 1.00 ] },
                "up": { "texture": "#1", "uv": [ 0.00, 0.00, 6.00, 1.00 ] },
                "down": { "texture": "#1", "uv": [ 0.00, 0.00, 6.00, 1.00 ] }
            }
        },
        {
            "name": "Stand2top2",
            "from": [ 10.00, 14.00, 3.00 ], 
            "to": [ 11.00, 15.00, 4.00 ], 
            "faces": {
                "north": { "texture": "#1", "uv": [ 0.00, 0.00, 1.00, 1.00 ] },
                "east": { "texture": "#1", "uv": [ 0.00, 0.00, 1.00, 1.00 ] },
                "south": { "texture": "#1", "uv": [ 0.00, 0.00, 1.00, 1.00 ] },
                "west": { "texture": "#1", "uv": [ 0.00, 0.00, 1.00, 1.00 ] },
                "up": { "texture": "#1", "uv": [ 0.00, 0.00, 1.00, 1.00 ] },
                "down": { "texture": "#1", "uv": [ 0.00, 0.00, 1.00, 1.00 ] }
            }
        },
        {
            "name": "Stand2top1",
            "from": [ 5.00, 14.00, 3.00 ], 
            "to": [ 6.00, 15.00, 4.00 ], 
            "faces": {
                "north": { "texture": "#1", "uv": [ 0.00, 0.00, 1.00, 1.00 ] },
                "east": { "texture": "#1", "uv": [ 0.00, 0.00, 1.00, 1.00 ] },
                "south": { "texture": "#1", "uv": [ 0.00, 0.00, 1.00, 1.00 ] },
                "west": { "texture": "#1", "uv": [ 0.00, 0.00, 1.00, 1.00 ] },
                "up": { "texture": "#1", "uv": [ 0.00, 0.00, 1.00, 1.00 ] },
                "down": { "texture": "#1", "uv": [ 0.00, 0.00, 1.00, 1.00 ] }
            }
        },
        {
            "name": "Stand2",
            "from": [ 7.00, 2.00, 3.00 ], 
            "to": [ 9.00, 13.00, 4.00 ], 
            "faces": {
                "north": { "texture": "#1", "uv": [ 13.00, 1.00, 15.00, 12.00 ] },
                "east": { "texture": "#1", "uv": [ 14.00, 1.00, 15.00, 12.00 ] },
                "south": { "texture": "#1", "uv": [ 13.00, 1.00, 15.00, 12.00 ] },
                "west": { "texture": "#1", "uv": [ 14.00, 1.00, 15.00, 12.00 ] },
                "up": { "texture": "#1", "uv": [ 1.00, 1.00, 3.00, 2.00 ] },
                "down": { "texture": "#1", "uv": [ 1.00, 1.00, 3.00, 2.00 ] }
            }
        },
        {
            "name": "Stand1",
            "from": [ 7.00, 2.00, 12.00 ], 
            "to": [ 9.00, 13.00, 13.00 ], 
            "faces": {
                "north": { "texture": "#1", "uv": [ 13.00, 1.00, 15.00, 12.00 ] },
                "east": { "texture": "#1", "uv": [ 14.00, 1.00, 15.00, 12.00 ] },
                "south": { "texture": "#1", "uv": [ 13.00, 1.00, 15.00, 12.00 ] },
                "west": { "texture": "#1", "uv": [ 14.00, 1.00, 15.00, 12.00 ] },
                "up": { "texture": "#1", "uv": [ 1.00, 1.00, 3.00, 2.00 ] },
                "down": { "texture": "#1", "uv": [ 1.00, 1.00, 3.00, 2.00 ] }
            }
        },
        {
            "name": "Middle1",
            "from": [ 7.00, 7.00, 4.00 ], 
            "to": [ 9.00, 8.00, 6.00 ], 
            "faces": {
                "north": { "texture": "#1", "uv": [ 1.00, 1.00, 3.00, 2.00 ] },
                "east": { "texture": "#1", "uv": [ 1.00, 1.00, 3.00, 2.00 ] },
                "south": { "texture": "#1", "uv": [ 1.00, 1.00, 3.00, 2.00 ] },
                "west": { "texture": "#1", "uv": [ 1.00, 1.00, 3.00, 2.00 ] },
                "up": { "texture": "#1", "uv": [ 1.00, 1.00, 3.00, 3.00 ] },
                "down": { "texture": "#1", "uv": [ 1.00, 1.00, 3.00, 3.00 ] }
            }
        },
        {
            "name": "Middle2",
            "from": [ 7.00, 7.00, 10.00 ], 
            "to": [ 9.00, 8.00, 12.00 ], 
            "faces": {
                "north": { "texture": "#1", "uv": [ 1.00, 1.00, 3.00, 2.00 ] },
                "east": { "texture": "#1", "uv": [ 1.00, 1.00, 3.00, 2.00 ] },
                "south": { "texture": "#1", "uv": [ 1.00, 1.00, 3.00, 2.00 ] },
                "west": { "texture": "#1", "uv": [ 1.00, 1.00, 3.00, 2.00 ] },
                "up": { "texture": "#1", "uv": [ 1.00, 1.00, 3.00, 3.00 ] },
                "down": { "texture": "#1", "uv": [ 1.00, 1.00, 3.00, 3.00 ] }
            }
        },
        {
            "name": "Middle3",
            "from": [ 6.00, 7.00, 6.00 ], 
            "to": [ 10.00, 8.00, 7.00 ], 
            "faces": {
                "north": { "texture": "#1", "uv": [ 0.00, 0.00, 4.00, 1.00 ] },
                "east": { "texture": "#1", "uv": [ 0.00, 0.00, 1.00, 1.00 ] },
                "south": { "texture": "#1", "uv": [ 0.00, 0.00, 4.00, 1.00 ] },
                "west": { "texture": "#1", "uv": [ 0.00, 0.00, 1.00, 1.00 ] },
                "up": { "texture": "#1", "uv": [ 0.00, 0.00, 4.00, 1.00 ] },
                "down": { "texture": "#1", "uv": [ 0.00, 0.00, 4.00, 1.00 ] }
            }
        },
        {
            "name": "Middle4",
            "from": [ 6.00, 7.00, 9.00 ], 
            "to": [ 10.00, 8.00, 10.00 ], 
            "faces": {
                "north": { "texture": "#1", "uv": [ 0.00, 0.00, 4.00, 1.00 ] },
                "east": { "texture": "#1", "uv": [ 0.00, 0.00, 1.00, 1.00 ] },
                "south": { "texture": "#1", "uv": [ 0.00, 0.00, 4.00, 1.00 ] },
                "west": { "texture": "#1", "uv": [ 0.00, 0.00, 1.00, 1.00 ] },
                "up": { "texture": "#1", "uv": [ 0.00, 0.00, 4.00, 1.00 ] },
                "down": { "texture": "#1", "uv": [ 0.00, 0.00, 4.00, 1.00 ] }
            }
        },
        {
            "name": "Middle5",
            "from": [ 6.00, 7.00, 7.00 ], 
            "to": [ 7.00, 8.00, 9.00 ], 
            "faces": {
                "north": { "texture": "#1", "uv": [ 0.00, 0.00, 1.00, 1.00 ] },
                "east": { "texture": "#1", "uv": [ 0.00, 0.00, 2.00, 1.00 ] },
                "south": { "texture": "#1", "uv": [ 0.00, 0.00, 1.00, 1.00 ] },
                "west": { "texture": "#1", "uv": [ 0.00, 0.00, 2.00, 1.00 ] },
                "up": { "texture": "#1", "uv": [ 0.00, 0.00, 1.00, 2.00 ] },
                "down": { "texture": "#1", "uv": [ 0.00, 0.00, 1.00, 2.00 ] }
            }
        },
        {
            "name": "Middle6",
            "from": [ 9.00, 7.00, 7.00 ], 
            "to": [ 10.00, 8.00, 9.00 ], 
            "faces": {
                "north": { "texture": "#1", "uv": [ 0.00, 0.00, 1.00, 1.00 ] },
                "east": { "texture": "#1", "uv": [ 0.00, 0.00, 2.00, 1.00 ] },
                "south": { "texture": "#1", "uv": [ 0.00, 0.00, 1.00, 1.00 ] },
                "west": { "texture": "#1", "uv": [ 0.00, 0.00, 2.00, 1.00 ] },
                "up": { "texture": "#1", "uv": [ 0.00, 0.00, 1.00, 2.00 ] },
                "down": { "texture": "#1", "uv": [ 0.00, 0.00, 1.00, 2.00 ] }
            }
        },
        {
            "name": "Cube",
            "from": [ 7.00, 7.00, 7.00 ], 
            "to": [ 9.00, 7.00, 9.00 ], 
            "faces": {
                "north": { "texture": "#2", "uv": [ 0.00, 0.00, 2.00, 0.00 ] },
                "up": { "texture": "#2", "uv": [ 1.00, 15.00, 15.00, 1.00 ] },
                "down": { "texture": "#2", "uv": [ 1.00, 15.00, 15.00, 1.00 ] }
            }
        }
    ]
}